aquila_flow-0.1.0.dist-info/METADATA
aquila_flow-0.1.0.dist-info/WHEEL
aquila_flow/__init__.py
aquila_flow/aquila_flow.cp312-win_amd64.pyd
aquila_flow-0.1.0.dist-info/RECORD
